cloth_tools/__init__.py
cloth_tools/bounding_boxes.py
cloth_tools/config.py
cloth_tools/motion_blur_detector.py
cloth_tools/multiprocess_viewer.py
cloth_tools/trajectory_execution.py
cloth_tools/wrench_smoother.py
cloth_tools/annotation/__init__.py
cloth_tools/annotation/grasp_annotation.py
cloth_tools/controllers/__init__.py
cloth_tools/controllers/basic_home_controller.py
cloth_tools/controllers/controller.py
cloth_tools/controllers/dry_run_grasp_controller.py
cloth_tools/controllers/grasp_hanging_controller.py
cloth_tools/controllers/grasp_highest_controller.py
cloth_tools/controllers/grasp_lowest_controller.py
cloth_tools/controllers/hang_controller.py
cloth_tools/controllers/home_controller.py
cloth_tools/controllers/stretch_controller.py
cloth_tools/dataset/__init__.py
cloth_tools/dataset/bookkeeping.py
cloth_tools/dataset/collection.py
cloth_tools/dataset/download.py
cloth_tools/dataset/format.py
cloth_tools/dataset/upload.py
cloth_tools/drake/__init__.py
cloth_tools/drake/scenes.py
cloth_tools/kinematics/__init__.py
cloth_tools/kinematics/constants.py
cloth_tools/kinematics/inverse_kinematics.py
cloth_tools/planning/__init__.py
cloth_tools/planning/grasp_planning.py
cloth_tools/point_clouds/__init__.py
cloth_tools/point_clouds/camera.py
cloth_tools/point_clouds/cloth_detection.py
cloth_tools/point_clouds/operations.py
cloth_tools/stations/__init__.py
cloth_tools/stations/competition_station.py
cloth_tools/stations/coordinate_frames.py
cloth_tools/stations/dual_arm_station.py
cloth_tools/visualization/__init__.py
cloth_tools/visualization/open3d.py
cloth_tools/visualization/opencv.py
cloth_tools/visualization/rerun.py
cloth_tools-0.3.2.dist-info/METADATA
cloth_tools-0.3.2.dist-info/WHEEL
cloth_tools-0.3.2.dist-info/top_level.txt
cloth_tools-0.3.2.dist-info/RECORD
