Metadata-Version: 2.1
Name: cloth-tools
Version: 0.3.2
Summary: Official package for the ICRA 2024 Cloth Competition
Author-email: Victor-Louis De Gusseme <victorlouisdg@gmail.com>
Project-URL: Homepage, https://github.com/Victorlouisdg/cloth-competition
Project-URL: Issues, https://github.com/Victorlouisdg/cloth-competition/issues
Classifier: Programming Language :: Python :: 3
Classifier: License :: OSI Approved :: MIT License
Classifier: Operating System :: OS Independent
Requires-Python: >=3.10
Requires-Dist: numpy
Requires-Dist: click
Requires-Dist: rerun-sdk
Requires-Dist: tqdm
Requires-Dist: requests
Requires-Dist: airo-planner
